minima_winput/__init__.py
minima_winput/core.py
minima_winput-0.1.0.dist-info/licenses/LICENSE
minima_winput-0.1.0.dist-info/METADATA
minima_winput-0.1.0.dist-info/WHEEL
minima_winput-0.1.0.dist-info/top_level.txt
minima_winput-0.1.0.dist-info/RECORD
