Metadata-Version: 2.4
Name: minima-winput
Version: 0.1.0
Summary: Minimalist Windows input emulation using SendInput API with hardware scan codes
License: MIT
Project-URL: Repository, https://github.com/yourusername/minima-winput
Keywords: windows,input,automation,sendinput,keyboard,mouse,hid
Requires-Python: >=3.8
License-File: LICENSE
Dynamic: license-file
